pymytools/__init__.py
pymytools/assets/sounds/life_is.wav
pymytools/constants.py
pymytools/diagnostics.py
pymytools/etc.py
pymytools/indices.py
pymytools/logger.py
pymytools/progress.py
pymytools/randoms.py
pymytools/special/__init__.py
pymytools/special/_ellipe.py
pymytools/special/_ellipk.py
pymytools-0.1.17.dist-info/WHEEL
pymytools-0.1.17.dist-info/METADATA
pymytools-0.1.17.dist-info/RECORD
