Metadata-Version: 2.1
Name: pymytools
Version: 0.1.17
Summary: Tools used in my pystops project.
Author: Kyoungseoun Chung
Author-email: kyoungseoun.chung@gmail.com
Requires-Python: >=3.10,<3.12
Classifier: Programming Language :: Python :: 3
Classifier: Programming Language :: Python :: 3.10
Requires-Dist: h5py (>=3.8.0,<4.0.0)
Requires-Dist: pandas (>=1.5.3,<2.0.0)
Requires-Dist: pyevtk (>=1.5.0,<2.0.0)
Requires-Dist: pymyplot (>=0.2.7,<0.3.0)
Requires-Dist: rich (>=13.3.2,<14.0.0)
Requires-Dist: scipy (>=1.10.1,<2.0.0)
Requires-Dist: simpleaudio (>=1.0.4,<2.0.0)
Requires-Dist: tensorboard (>=2.12.0,<3.0.0)
Requires-Dist: torch (>=2.0.0,<3.0.0)
Requires-Dist: tqdm (>=4.65.0,<5.0.0)
Requires-Dist: vtk (>=9.2.6,<10.0.0)
